aisignal/__init__.py
aisignal/cli.py
aisignal/core/__init__.py
aisignal/core/adapters/__init__.py
aisignal/core/adapters/config_adapter.py
aisignal/core/adapters/content_adapter.py
aisignal/core/adapters/resource_adapter.py
aisignal/core/config_schema.py
aisignal/core/export.py
aisignal/core/filters.py
aisignal/core/interfaces.py
aisignal/core/models.py
aisignal/core/resource_manager.py
aisignal/core/services/__init__.py
aisignal/core/services/config_service.py
aisignal/core/services/content_service.py
aisignal/core/services/core_service.py
aisignal/core/services/event_bus.py
aisignal/core/services/storage_service.py
aisignal/core/sync_exceptions.py
aisignal/core/sync_status.py
aisignal/core/token_tracker.py
aisignal/services/__init__.py
aisignal/ui/__init__.py
aisignal/ui/textual/__init__.py
aisignal/ui/textual/app.py
aisignal/ui/textual/screens/__init__.py
aisignal/ui/textual/screens/base.py
aisignal/ui/textual/screens/config.py
aisignal/ui/textual/screens/main.py
aisignal/ui/textual/screens/modals/__init__.py
aisignal/ui/textual/screens/modals/sync_status_modal.py
aisignal/ui/textual/screens/modals/token_usage_modal.py
aisignal/ui/textual/screens/resource/__init__.py
aisignal/ui/textual/screens/resource/detail.py
aisignal/ui/textual/screens/resource/note.py
aisignal/ui/textual/screens/share.py
aisignal/ui/textual/styles/app.tcss
aisignal/utils/__init__.py
aisignal/utils/advanced_service_container.py
aisignal/utils/feed_detector.py
aisignal/utils/service_container.py
ai_signal-0.11.0.dist-info/METADATA
ai_signal-0.11.0.dist-info/WHEEL
ai_signal-0.11.0.dist-info/entry_points.txt
ai_signal-0.11.0.dist-info/licenses/LICENSE
ai_signal-0.11.0.dist-info/RECORD
