Metadata-Version: 2.4
Name: ai-signal
Version: 0.11.0
Summary: Terminal-based AI curator that turns information noise into meaningful signal
License: MIT
License-File: LICENSE
Keywords: ai,curation,terminal,tui,textual,content,aggregator,filter
Author: Guglielmo Celata
Author-email: guglielmo.celata@gmail.com
Requires-Python: >=3.9,<4.0
Classifier: Development Status :: 3 - Alpha
Classifier: Environment :: Console
Classifier: Intended Audience :: Developers
Classifier: Intended Audience :: End Users/Desktop
Classifier: License :: OSI Approved :: MIT License
Classifier: Programming Language :: Python :: 3
Classifier: Programming Language :: Python :: 3.9
Classifier: Programming Language :: Python :: 3.10
Classifier: Programming Language :: Python :: 3.11
Classifier: Programming Language :: Python :: 3.12
Classifier: Programming Language :: Python :: 3.13
Classifier: Programming Language :: Python :: 3.14
Classifier: Topic :: Internet :: WWW/HTTP :: Dynamic Content
Classifier: Topic :: Scientific/Engineering :: Artificial Intelligence
Classifier: Topic :: Terminals
Classifier: Topic :: Text Processing :: Filters
Classifier: Topic :: Utilities
Requires-Dist: aiohttp (>=3.9.1,<4.0.0)
Requires-Dist: beautifulsoup4 (>=4.12.3,<5.0.0)
Requires-Dist: feedparser (>=6.0.11,<7.0.0)
Requires-Dist: html2text (>=2024.2.26,<2025.0.0)
Requires-Dist: lxml-html-clean (>=0.4.1,<0.5.0)
Requires-Dist: markdown (>=3.7,<4.0)
Requires-Dist: openai (>=1.3.0,<2.0.0)
Requires-Dist: python-frontmatter (>=1.0.0,<2.0.0)
Requires-Dist: pyyaml (>=6.0,<7.0)
Requires-Dist: readability-lxml (>=0.8.1,<0.9.0)
Requires-Dist: requests (>=2.32.3,<3.0.0)
Requires-Dist: rich (>=13.9.4,<14.0.0)
Requires-Dist: textual (>=0.87.0,<0.88.0)
Requires-Dist: toml (>=0.10.2,<0.11.0)
Requires-Dist: typer (>=0.13.1,<0.14.0)
Project-URL: Documentation, https://github.com/guglielmo/ai-signal#readme
Project-URL: Homepage, https://github.com/guglielmo/ai-signal
Project-URL: Repository, https://github.com/guglielmo/ai-signal
